jupyterlab_jherng/__init__.py
jupyterlab_jherng/_version.py
jupyterlab_jherng-0.1.3.data/data/share/jupyter/labextensions/@jherng/jupyterlab-jherng/package.json
jupyterlab_jherng-0.1.3.data/data/share/jupyter/labextensions/@jherng/jupyterlab-jherng/static/509.ed5f41e6585618e73902.js
jupyterlab_jherng-0.1.3.data/data/share/jupyter/labextensions/@jherng/jupyterlab-jherng/static/remoteEntry.41e347427f24488358b6.js
jupyterlab_jherng-0.1.3.data/data/share/jupyter/labextensions/@jherng/jupyterlab-jherng/static/style.js
jupyterlab_jherng-0.1.3.data/data/share/jupyter/labextensions/@jherng/jupyterlab-jherng/static/third-party-licenses.json
jupyterlab_jherng-0.1.3.data/data/share/jupyter/labextensions/@jherng/jupyterlab-jherng/themes/@jherng/jupyterlab-jherng/3127f0b873387ee37e20.ttf
jupyterlab_jherng-0.1.3.data/data/share/jupyter/labextensions/@jherng/jupyterlab-jherng/themes/@jherng/jupyterlab-jherng/6edc39c3df4fd1d4502a.ttf
jupyterlab_jherng-0.1.3.data/data/share/jupyter/labextensions/@jherng/jupyterlab-jherng/themes/@jherng/jupyterlab-jherng/index.css
jupyterlab_jherng-0.1.3.data/data/share/jupyter/labextensions/@jherng/jupyterlab-jherng/themes/@jherng/jupyterlab-jherng/index.js
jupyterlab_jherng-0.1.3.data/data/share/jupyter/labextensions/@jherng/jupyterlab-jherng/install.json
jupyterlab_jherng-0.1.3.dist-info/METADATA
jupyterlab_jherng-0.1.3.dist-info/WHEEL
jupyterlab_jherng-0.1.3.dist-info/licenses/LICENSE
jupyterlab_jherng-0.1.3.dist-info/RECORD
