Metadata-Version: 2.1
Name: jupyterlab-jherng
Version: 0.1.3
Summary: A JupyterLab theme for me.
Project-URL: Homepage, https://github.com/hongjiaherng/jupyterlab-jherng
Project-URL: Bug Tracker, https://github.com/hongjiaherng/jupyterlab-jherng/issues
Project-URL: Repository, https://github.com/hongjiaherng/jupyterlab-jherng.git
Author-email: jherng <jiaherng2001@gmail.com>
License: BSD 3-Clause License
License-File: LICENSE
Classifier: Framework :: Jupyter
Classifier: Framework :: Jupyter :: JupyterLab
Classifier: Framework :: Jupyter :: JupyterLab :: 4
Classifier: Framework :: Jupyter :: JupyterLab :: Extensions
Classifier: Framework :: Jupyter :: JupyterLab :: Extensions :: Prebuilt
Classifier: License :: OSI Approved :: BSD License
Classifier: Programming Language :: Python
Classifier: Programming Language :: Python :: 3
Classifier: Programming Language :: Python :: 3.8
Classifier: Programming Language :: Python :: 3.9
Classifier: Programming Language :: Python :: 3.10
Classifier: Programming Language :: Python :: 3.11
Classifier: Programming Language :: Python :: 3.12
Requires-Python: >=3.8
